smartq_llm_app_utils/__init__.py
smartq_llm_app_utils/model.py
smartq_llm_app_utils/retrieval.py
smartq_llm_app_utils-0.0.1.post1708928286.dist-info/METADATA
smartq_llm_app_utils-0.0.1.post1708928286.dist-info/WHEEL
smartq_llm_app_utils-0.0.1.post1708928286.dist-info/RECORD
