Metadata-Version: 2.1
Name: smartq-llm-app-utils
Version: 0.0.1.post1708928286
Summary: 
Author: hwacom_sc_rd2
Author-email: aiot.hwacom@gmail.com
Requires-Python: >=3.9.0,<4.0.0
Classifier: Programming Language :: Python :: 3
Classifier: Programming Language :: Python :: 3.9
Classifier: Programming Language :: Python :: 3.10
Classifier: Programming Language :: Python :: 3.11
Requires-Dist: langchain (>=0.1.4,<0.2.0)
Requires-Dist: langchain-community (>=0.0.16,<0.0.17)
Requires-Dist: langchain-openai (>=0.0.5,<0.0.6)
Requires-Dist: pydantic-settings (>=2.1.0,<3.0.0)
Requires-Dist: pytest (>=8.0.0,<9.0.0)
Requires-Dist: qdrant-client (>=1.7.3,<2.0.0)
